Metadata-Version: 1.1
Name: basiccalculatorofme
Version: 0.0.1
Summary: A Very basic calc
Home-page: UNKNOWN
Author: Pranav Chandran
Author-email: pranav.chandran@gmail.com
License: UNKNOWN
Platform: UNKNOWN
Classifier: Development Status :: 5 - Production/Stable
Classifier: Intended Audience :: Education
Classifier: License :: OSI Approved :: MIT License
Classifier: Programming Language :: Python :: 3
